nornir_pyez/__init__.py
nornir_pyez/plugins/__init__.py
nornir_pyez/plugins/connections/__init__.py
nornir_pyez/plugins/tasks/__init__.py
nornir_pyez/plugins/tasks/pyez_arp_noresolve.py
nornir_pyez/plugins/tasks/pyez_chassis_inventory.py
nornir_pyez/plugins/tasks/pyez_checksum.py
nornir_pyez/plugins/tasks/pyez_cmd.py
nornir_pyez/plugins/tasks/pyez_commit.py
nornir_pyez/plugins/tasks/pyez_config.py
nornir_pyez/plugins/tasks/pyez_diff.py
nornir_pyez/plugins/tasks/pyez_facts.py
nornir_pyez/plugins/tasks/pyez_get_config.py
nornir_pyez/plugins/tasks/pyez_int_terse.py
nornir_pyez/plugins/tasks/pyez_optics_diags.py
nornir_pyez/plugins/tasks/pyez_rollback.py
nornir_pyez/plugins/tasks/pyez_route_info.py
nornir_pyez/plugins/tasks/pyez_rpc.py
nornir_pyez/plugins/tasks/pyez_scp.py
nornir_pyez/plugins/tasks/pyez_sec_nat.py
nornir_pyez/plugins/tasks/pyez_sec_policy.py
nornir_pyez/plugins/tasks/pyez_sec_vpn.py
nornir_pyez/plugins/tasks/pyez_sec_zones.py
nornir_pyez-0.3.0.dist-info/LICENSE
nornir_pyez-0.3.0.dist-info/METADATA
nornir_pyez-0.3.0.dist-info/WHEEL
nornir_pyez-0.3.0.dist-info/entry_points.txt
nornir_pyez-0.3.0.dist-info/RECORD
